setup.py
memoise/__init__.py
memoise/memoise.py
memoise.egg-info/PKG-INFO
memoise.egg-info/SOURCES.txt
memoise.egg-info/dependency_links.txt
memoise.egg-info/entry_points.txt
memoise.egg-info/requires.txt
memoise.egg-info/top_level.txt