Metadata-Version: 1.1
Name: memoise
Version: 0.16.1
Summary: Memoise decorator.
Home-page: https://github.com/jfjlaros/memoise
Author: Jeroen F.J. Laros
Author-email: jlaros@fixedpoint.nl
License: MIT License
Keywords: optimisation
Platform: any
Classifier: Development Status :: 3 - Alpha
Classifier: Intended Audience :: Science/Research
Classifier: Intended Audience :: Developers
Classifier: Operating System :: OS Independent
Classifier: Programming Language :: Python
Classifier: Topic :: Scientific/Engineering
